odoo8_addon_stock_disable_barcode_interface-8.0.1.0.0-py2.7-nspkg.pth
odoo_addons/stock_disable_barcode_interface/__openerp__.py
odoo_addons/stock_disable_barcode_interface/__init__.py
odoo_addons/stock_disable_barcode_interface/README.rst
odoo_addons/stock_disable_barcode_interface/security/stock_disable_barcode_interface_security.xml
odoo_addons/stock_disable_barcode_interface/models/stock_config_settings.py
odoo_addons/stock_disable_barcode_interface/models/__init__.py
odoo_addons/stock_disable_barcode_interface/views/stock_picking_type_view.xml
odoo_addons/stock_disable_barcode_interface/views/stock_config_settings_view.xml
odoo_addons/stock_disable_barcode_interface/views/stock_picking_view.xml
odoo8_addon_stock_disable_barcode_interface-8.0.1.0.0.dist-info/top_level.txt
odoo8_addon_stock_disable_barcode_interface-8.0.1.0.0.dist-info/WHEEL
odoo8_addon_stock_disable_barcode_interface-8.0.1.0.0.dist-info/RECORD
odoo8_addon_stock_disable_barcode_interface-8.0.1.0.0.dist-info/metadata.json
odoo8_addon_stock_disable_barcode_interface-8.0.1.0.0.dist-info/DESCRIPTION.rst
odoo8_addon_stock_disable_barcode_interface-8.0.1.0.0.dist-info/METADATA
odoo8_addon_stock_disable_barcode_interface-8.0.1.0.0.dist-info/namespace_packages.txt
