Metadata-Version: 2.0
Name: odoo8-addon-stock-disable-barcode-interface
Version: 8.0.1.0.0
Summary: Disable and enable (configurable) the barcode interface
Home-page: http://www.onestein.eu
Author: ONESTEiN BV, Odoo Community Association (OCA)
Author-email: support@odoo-community.org
License: AGPL-3
Platform: UNKNOWN
Requires-Dist: odoo (<9.0a,>=8.0a)
Classifier: Programming Language :: Python :: 2.7
Classifier: Framework :: Odoo
Classifier: License :: OSI Approved :: GNU Affero General Public License v3
